datawarehouse_connector/__init__.py
datawarehouse_connector/connector.py
datawarehouse_connector/constants.py
datawarehouse_connector/postgres_session.py
datawarehouse_connector/redshift_session.py
datawarehouse_connector/snowflake_session.py
datawarehouse_connector/utils.py
datawarehouse_connector/validate.py
datawarehouse_connector-0.1.3.dist-info/LICENSE
datawarehouse_connector-0.1.3.dist-info/METADATA
datawarehouse_connector-0.1.3.dist-info/WHEEL
datawarehouse_connector-0.1.3.dist-info/top_level.txt
datawarehouse_connector-0.1.3.dist-info/RECORD
