Metadata-Version: 2.1
Name: datawarehouse-connector
Version: 0.1.3
Summary: A package for database session management
Home-page: https://github.com/Chandani7250/datawarehouse_connector
Author: Chandani Kumari
Author-email: Chandani@coditation.com
License: UNKNOWN
Platform: UNKNOWN
Classifier: Programming Language :: Python :: 3
Classifier: License :: OSI Approved :: MIT License
Classifier: Operating System :: OS Independent
Requires-Python: >=3.8
Requires-Dist: psycopg2-binary
Requires-Dist: redshift-connector
Requires-Dist: snowflake-connector-python
Requires-Dist: snowflake-sqlalchemy
Requires-Dist: SQLAlchemy
Requires-Dist: sqlalchemy-redshift
Requires-Dist: urllib3
